{
  "informatyka": [
    "-14.439685",
    "29.112547",
    "-15.50721"
  ],
  "matematyka": [
    "-10.046048",
    "11.674302",
    "13.091428"
  ],
  "mechanika": [
    "-30.516735",
    "-25.690317",
    "-34.504017"
  ],
  "biologia": [
    "16.87455",
    "-3.2776754",
    "11.450432"
  ],
  "biotechnologia": [
    "6.5339794",
    "12.656677",
    "4.239885"
  ],
  "biochemia": [
    "1.8252494",
    "-1.6868951",
    "13.778082"
  ],
  "inżynieria oprogramowania": [
    "-21.639812",
    "7.836722",
    "-9.094035"
  ],
  "sieć": [
    "15.314365",
    "11.501716",
    "-19.573164"
  ],
  "elektronika": [
    "16.18898",
    "29.401329",
    "-5.423357"
  ],
  "telekomunikacja": [
    "-0.0779992",
    "20.63518",
    "-20.739864"
  ],
  "inżynieria biomedyczna": [
    "-22.241081",
    "6.159388",
    "-6.1915016"
  ],
  "inżynieria mechaniczna": [
    "-23.94088",
    "7.593729",
    "-7.772418"
  ],
  "energetyka": [
    "24.43075",
    "51.181217",
    "8.99107"
  ],
  "elektrotechnika": [
    "15.231368",
    "3.2978685",
    "-6.2565713"
  ],
  "automatyka i robotyka": [
    "4.338598",
    "-15.148304",
    "13.047938"
  ],
  "elektrotechnika stosowana": [
    "17.701115",
    "4.1747227",
    "-7.115428"
  ],
  "chemia": [
    "-4.3112783",
    "39.118534",
    "1.6206602"
  ],
  "inżynieria chemiczna": [
    "-20.606306",
    "5.6739745",
    "-8.231514"
  ],
  "nanotechnologia": [
    "-5.3848042",
    "-23.11744",
    "-0.14883816"
  ],
  "informatyka stosowana": [
    "-6.080803",
    "21.189184",
    "-15.839243"
  ],
  "statystyka": [
    "46.32573",
    "21.538593",
    "26.729609"
  ],
  "mechatronika": [
    "-17.515749",
    "-21.898844",
    "51.398857"
  ],
  "inżynieria mechatroniczna": [
    "-23.01214",
    "5.501314",
    "-8.612038"
  ],
  "fizyka": [
    "-12.573861",
    "-7.7387614",
    "10.915111"
  ],
  "astronomia": [
    "28.527494",
    "22.560722",
    "-40.459087"
  ],
  "chemia stosowana": [
    "-4.3112783",
    "39.118534",
    "1.6206602"
  ],
  "filozofia": [
    "-3.9470277",
    "23.710117",
    "11.273353"
  ],
  "kognitywistyka": [
    "-9.500679",
    "22.051535",
    "-6.9111714"
  ],
  "etyka": [
    "-2.4312897",
    "24.79488",
    "12.498581"
  ],
  "historia": [
    "10.943048",
    "-12.990874",
    "-4.6952143"
  ],
  "socjologia": [
    "6.2905293",
    "6.976152",
    "-23.029644"
  ],
  "politologia": [
    "4.607169",
    "-2.2651243",
    "-14.664845"
  ],
  "zarządzanie": [
    "-7.14192",
    "23.639618",
    "33.977325"
  ],
  "komunikacja społeczna": [
    "0.5630684",
    "18.936625",
    "-22.14907"
  ],
  "stosunki międzynarodowe": [
    "8.461507",
    "-25.49296",
    "-37.11181"
  ],
  "teleinformatyka": [
    "1.8170154",
    "24.057346",
    "-12.320177"
  ],
  "bezpieczeństwo": [
    "-9.697042",
    "40.15083",
    "24.965479"
  ],
  "architektura": [
    "-20.289848",
    "-31.726128",
    "-22.712555"
  ],
  "urbanistyka": [
    "-2.2846975",
    "-3.2873602",
    "-1.0071566"
  ],
  "architektura krajobrazu": [
    "11.087758",
    "-44.103928",
    "1.2174882"
  ],
  "psychologia": [
    "4.8765078",
    "8.448007",
    "-23.837034"
  ],
  "archeologia": [
    "46.28932",
    "-4.945459",
    "3.8328784"
  ],
  "filologia polska": [
    "-43.153427",
    "-10.793361",
    "20.970913"
  ],
  "anglistyka": [
    "1.0896436",
    "-13.654586",
    "-16.861315"
  ],
  "germanistyka": [
    "30.60793",
    "-39.115246",
    "3.49435"
  ],
  "ekonomia": [
    "7.0758457",
    "13.911571",
    "-39.57962"
  ],
  "inżynieria okrętowa": [
    "-23.842497",
    "13.221978",
    "-4.7211356"
  ],
  "technologia morska": [
    "24.794495",
    "12.865107",
    "-0.80504847"
  ],
  "logistyka morska": [
    "-44.1485",
    "22.724398",
    "-15.750684"
  ],
  "sztuczna inteligencja": [
    "-13.629104",
    "-13.340524",
    "-8.383263"
  ],
  "inżynieria materiałowa": [
    "-19.384727",
    "8.664874",
    "-2.5169318"
  ],
  "technologia chemiczna": [
    "24.24112",
    "10.947984",
    "-0.9075431"
  ],
  "fizyka techniczna": [
    "-16.032507",
    "-5.8870845",
    "9.562972"
  ],
  "matematyka stosowana": [
    "-13.111578",
    "12.3988495",
    "14.963469"
  ],
  "chemia techniczna": [
    "29.12975",
    "-14.140153",
    "30.466679"
  ],
  "chemia kosmetyczna": [
    "19.255135",
    "3.9969828",
    "56.287354"
  ],
  "logistyka": [
    "-40.043808",
    "27.720922",
    "-2.9124265"
  ],
  "rolnictwo": [
    "2.153707",
    "12.471955",
    "-10.548985"
  ],
  "ochrona środowiska": [
    "20.743347",
    "17.433708",
    "-15.136766"
  ],
  "inżynieria środowiska": [
    "-27.170982",
    "10.016662",
    "-6.0380096"
  ],
  "żywienie człowieka": [
    "-7.6229606",
    "20.98838",
    "-3.9425058"
  ],
  "technologia żywności": [
    "25.213936",
    "11.620754",
    "0.7012478"
  ],
  "dietetyka": [
    "-8.56219",
    "21.503218",
    "-5.393554"
  ],
  "medycyna weterynaryjna": [
    "-4.624005",
    "35.358128",
    "0.90283126"
  ],
  "higiena weterynaryjna": [
    "-6.991829",
    "20.653538",
    "-2.976949"
  ],
  "nauka o zwierzętach": [
    "8.996701",
    "-14.095128",
    "-0.34802914"
  ],
  "leśnictwo": [
    "1.2828451",
    "11.496205",
    "-9.327307"
  ],
  "ochrona przyrody": [
    "20.258482",
    "18.4218",
    "-15.132704"
  ],
  "zootechnika": [
    "42.217392",
    "-8.028652",
    "21.311934"
  ],
  "hortiterapia": [
    "0.9422605",
    "25.014164",
    "-10.424443"
  ],
  "inżynieria ogrodnicza": [
    "-20.958487",
    "3.2180455",
    "-10.920062"
  ],
  "technologia drewna": [
    "26.173359",
    "11.438533",
    "-1.0425562"
  ],
  "meblarstwo": [
    "13.601727",
    "27.751095",
    "-5.098005"
  ],
  "budownictwo": [
    "-0.5897155",
    "7.840497",
    "-4.7639213"
  ],
  "inżynieria produkcji": [
    "52.458267",
    "28.297266",
    "1.6925992"
  ],
  "informatyka fizyczna": [
    "10.054228",
    "-8.496839",
    "51.543793"
  ],
  "chemia analityczna": [
    "-26.828087",
    "-40.35507",
    "30.291254"
  ],
  "chemiczny": [
    "-4.9536414",
    "-0.063528374",
    "-22.267862"
  ],
  "finanse": [
    "27.24982",
    "3.1745052",
    "10.239413"
  ],
  "prawo": [
    "8.248933",
    "-14.34732",
    "1.3083017"
  ],
  "administracja": [
    "27.063217",
    "3.268421",
    "11.3195915"
  ],
  "bezpieczeństwo narodowe": [
    "5.1393447",
    "14.325035",
    "31.07712"
  ]
}